multiplefilecomparison/__init__.py
multiplefilecomparison/docx_and_pdf.py
multiplefilecomparison/excel_compare.py
multiplefilecomparison-1.2.dist-info/LICENSE
multiplefilecomparison-1.2.dist-info/METADATA
multiplefilecomparison-1.2.dist-info/WHEEL
multiplefilecomparison-1.2.dist-info/top_level.txt
multiplefilecomparison-1.2.dist-info/RECORD
