Metadata-Version: 2.1
Name: multiplefilecomparison
Version: 1.2
Summary: It compares multiplefiles with the reference file
Author: Jai Narayan Jain
License: Copyright 2023 JAI NARAYAN JAIN
Requires-Python: <3.12,>=3.9
License-File: LICENSE
Requires-Dist: docx2pdf
Requires-Dist: PyPDF2
Requires-Dist: openpyxl
